MANIFEST.in
README.md
pyproject.toml
setup.py
galmex/Background_module.py
galmex/Cleaning_module.py
galmex/Detection_module.py
galmex/Flagging_module.py
galmex/Metrics_module.py
galmex/Petrosian_module.py
galmex/Segmentation_module.py
galmex/Utils_module.py
galmex/__init__.py
galmex/__main__.py
galmex/cleaning.c
galmex/cleaning.pyx
galmex/galmex_runner.py
galmex.egg-info/PKG-INFO
galmex.egg-info/SOURCES.txt
galmex.egg-info/dependency_links.txt
galmex.egg-info/entry_points.txt
galmex.egg-info/requires.txt
galmex.egg-info/top_level.txt
galmex/Azure-ttk-theme/azure.tcl
galmex/Azure-ttk-theme/theme/dark.tcl
galmex/Azure-ttk-theme/theme/light.tcl
galmex/Azure-ttk-theme/theme/dark/box-accent.png
galmex/Azure-ttk-theme/theme/dark/box-basic.png
galmex/Azure-ttk-theme/theme/dark/box-hover.png
galmex/Azure-ttk-theme/theme/dark/box-invalid.png
galmex/Azure-ttk-theme/theme/dark/button-hover.png
galmex/Azure-ttk-theme/theme/dark/card.png
galmex/Azure-ttk-theme/theme/dark/check-accent.png
galmex/Azure-ttk-theme/theme/dark/check-basic.png
galmex/Azure-ttk-theme/theme/dark/check-hover.png
galmex/Azure-ttk-theme/theme/dark/check-tri-accent.png
galmex/Azure-ttk-theme/theme/dark/check-tri-basic.png
galmex/Azure-ttk-theme/theme/dark/check-tri-hover.png
galmex/Azure-ttk-theme/theme/dark/circle-accent.png
galmex/Azure-ttk-theme/theme/dark/circle-basic.png
galmex/Azure-ttk-theme/theme/dark/circle-hover.png
galmex/Azure-ttk-theme/theme/dark/combo-button-basic.png
galmex/Azure-ttk-theme/theme/dark/combo-button-focus.png
galmex/Azure-ttk-theme/theme/dark/combo-button-hover.png
galmex/Azure-ttk-theme/theme/dark/down-accent.png
galmex/Azure-ttk-theme/theme/dark/down.png
galmex/Azure-ttk-theme/theme/dark/empty.png
galmex/Azure-ttk-theme/theme/dark/hor-accent.png
galmex/Azure-ttk-theme/theme/dark/hor-basic.png
galmex/Azure-ttk-theme/theme/dark/hor-hover.png
galmex/Azure-ttk-theme/theme/dark/notebook.png
galmex/Azure-ttk-theme/theme/dark/off-basic.png
galmex/Azure-ttk-theme/theme/dark/on-accent.png
galmex/Azure-ttk-theme/theme/dark/on-basic.png
galmex/Azure-ttk-theme/theme/dark/outline-basic.png
galmex/Azure-ttk-theme/theme/dark/outline-hover.png
